[
    {
        "image": "images/download.jpg",
        "title": "Slaughterhouse Five",
        "author": "Kurt Vonnegut",
        "genre": "Science fiction",
        "stars": 3.5,
        "pages": 100
    },
    {
        "image": "images/download.jpg",
        "title": "Norwegian Wood",
        "author": "Haruki Murakami",
        "genre": "Literary fiction",
        "stars": 4.03,
        "pages": 388
    },
    {
        "image": "images/download.jpg",
        "title": "Steve Jobs",
        "author": "Walter Isaacson",
        "genre": "Memoirs and biographies",
        "stars": 3.84,
        "pages": 201
    },
    {
        "image": "images/download.jpg",
        "title": "Ariel",
        "author": "Sylvia Plath",
        "genre": "Poetry",
        "stars": 5.0,
        "pages": 480
    }
  ]